{
  "db_name": "PostgreSQL",
  "query": "\n        SELECT\n            id,\n            user_id,\n            last_four,\n            brand,\n            exp_month,\n            exp_year,\n            is_default,\n            provider_card_id,\n            created_at\n        FROM payment_cards\n        WHERE user_id = $1\n        ORDER BY is_default DESC, created_at DESC\n        ",
  "describe": {
    "columns": [
      {
        "ordinal": 0,
        "name": "id",
        "type_info": "Uuid"
      },
      {
        "ordinal": 1,
        "name": "user_id",
        "type_info": "Uuid"
      },
      {
        "ordinal": 2,
        "name": "last_four",
        "type_info": "Varchar"
      },
      {
        "ordinal": 3,
        "name": "brand",
        "type_info": "Varchar"
      },
      {
        "ordinal": 4,
        "name": "exp_month",
        "type_info": "Int2"
      },
      {
        "ordinal": 5,
        "name": "exp_year",
        "type_info": "Int2"
      },
      {
        "ordinal": 6,
        "name": "is_default",
        "type_info": "Bool"
      },
      {
        "ordinal": 7,
        "name": "provider_card_id",
        "type_info": "Varchar"
      },
      {
        "ordinal": 8,
        "name": "created_at",
        "type_info": "Timestamptz"
      }
    ],
    "parameters": {
      "Left": [
        "Uuid"
      ]
    },
    "nullable": [
      false,
      false,
      false,
      false,
      false,
      false,
      false,
      false,
      false
    ]
  },
  "hash": "7ca0cfa65dbb787aacf84eff6dd066e51a7300b66d3fa17cd13c3d4d9bd2de4e"
}
